zsx_some_tools/__init__.py
zsx_some_tools/basic_tools.py
zsx_some_tools/bio_tools.py
zsx_some_tools/plot_tools.py
zsx_some_tools/read_write_tools.py
zsx_some_tools/setup.py
zsx_some_tools/za.py
zsx_some_tools/zsx_some_tools/__init__.py
zsx_some_tools/zsx_some_tools/basic_tools.py
zsx_some_tools/zsx_some_tools/bio_tools.py
zsx_some_tools/zsx_some_tools/plot_tools.py
zsx_some_tools/zsx_some_tools/read_write_tools.py
zsx_some_tools/zsx_some_tools/za.py
zsx_some_tools-2.1.0.dist-info/METADATA
zsx_some_tools-2.1.0.dist-info/WHEEL
zsx_some_tools-2.1.0.dist-info/top_level.txt
zsx_some_tools-2.1.0.dist-info/RECORD
